LICENSE
MANIFEST.in
README.rst
setup.py
gapic_google_cloud_speech_v1beta1.egg-info/PKG-INFO
gapic_google_cloud_speech_v1beta1.egg-info/SOURCES.txt
gapic_google_cloud_speech_v1beta1.egg-info/dependency_links.txt
gapic_google_cloud_speech_v1beta1.egg-info/namespace_packages.txt
gapic_google_cloud_speech_v1beta1.egg-info/requires.txt
gapic_google_cloud_speech_v1beta1.egg-info/top_level.txt
google/__init__.py
google/cloud/__init__.py
google/cloud/gapic/__init__.py
google/cloud/gapic/speech/__init__.py
google/cloud/gapic/speech/v1beta1/__init__.py
google/cloud/gapic/speech/v1beta1/enums.py
google/cloud/gapic/speech/v1beta1/speech_client.py
google/cloud/gapic/speech/v1beta1/speech_client_config.json