Metadata-Version: 1.1
Name: gapic-google-cloud-speech-v1beta1
Version: 0.15.0
Summary: GAPIC library for the Google Cloud Speech API
Home-page: https://github.com/googleapis/googleapis
Author: Google Inc
Author-email: googleapis-packages@google.com
License: Apache-2.0
Platform: UNKNOWN
Classifier: Intended Audience :: Developers
Classifier: Development Status :: 3 - Alpha
Classifier: Intended Audience :: Developers
Classifier: License :: OSI Approved :: Apache Software License
Classifier: Programming Language :: Python
Classifier: Programming Language :: Python :: 2
Classifier: Programming Language :: Python :: 2.7
Classifier: Programming Language :: Python :: 3
Classifier: Programming Language :: Python :: 3.4
Classifier: Programming Language :: Python :: 3.5
Classifier: Programming Language :: Python :: Implementation :: CPython
